charz_rust-0.2.3.dist-info/METADATA
charz_rust-0.2.3.dist-info/WHEEL
charz_rust-0.2.3.dist-info/licenses/LICENSE
charz_rust/__init__.py
charz_rust/_core.pyd
charz_rust/_core.pyi
charz_rust/py.typed
charz_rust-0.2.3.dist-info/RECORD
