Metadata-Version: 2.4
Name: charz-rust
Version: 0.2.3
Requires-Dist: charz>=0.1.2
License-File: LICENSE
Summary: Blazingly fast speed-ups for charz
Author-email: Havsalt <77575424+Havsalt@users.noreply.github.com>
Requires-Python: >=3.10
